tree_traversals.py
tree_traversals-0.1.0a0.dist-info/licenses/LICENSE
tree_traversals-0.1.0a0.dist-info/METADATA
tree_traversals-0.1.0a0.dist-info/WHEEL
tree_traversals-0.1.0a0.dist-info/top_level.txt
tree_traversals-0.1.0a0.dist-info/RECORD
