Metadata-Version: 2.4
Name: tree-traversals
Version: 0.1.0a0
Summary: Efficient and generic traversals for any Python tree structure with full ancestor paths.
Author-email: Jifeng Wu <jifengwu2k@gmail.com>
License-Expression: MIT
Project-URL: Homepage, https://github.com/jifengwu2k/tree-traversals
Project-URL: Bug Tracker, https://github.com/jifengwu2k/tree-traversals/issues
Classifier: Programming Language :: Python :: 2
Classifier: Programming Language :: Python :: 3
Classifier: Operating System :: OS Independent
Requires-Python: >=2
License-File: LICENSE
Requires-Dist: cowlist
Requires-Dist: typing; python_version < "3.5"
Dynamic: license-file
